Metadata-Version: 2.1
Name: schwicv
Version: 0.0.8
Summary: Schwi's Utilities
Home-page: https://github.com/Schwi88/SchwiCV
Author: Thomas Schwingenschlögl
Author-email: office@schwi.at
License: MIT
Platform: UNKNOWN
Classifier: License :: OSI Approved :: MIT License
Classifier: Programming Language :: Python :: 3
Classifier: Programming Language :: Python :: 3.7
Classifier: Programming Language :: Python :: 3.8
Classifier: Programming Language :: Python :: 3.9
Classifier: Programming Language :: Python :: 3.10
License-File: LICENSE
